opentelemetry/__init__.py
opentelemetry/instrumentation/__init__.py
opentelemetry/instrumentation/azure_aisearch/__init__.py
opentelemetry/instrumentation/azure_aisearch/span_processor.py
opentelemetry/instrumentation/azure_aisearch/version.py
opentelemetry/instrumentation/azure_aisearch/wrappers.py
opentelemetry_instrumentation_azure_aisearch-0.1.2.dist-info/METADATA
opentelemetry_instrumentation_azure_aisearch-0.1.2.dist-info/WHEEL
opentelemetry_instrumentation_azure_aisearch-0.1.2.dist-info/RECORD
