Metadata-Version: 2.4
Name: opentelemetry-instrumentation-azure-aisearch
Version: 0.1.2
Summary: OpenTelemetry Azure AI Search instrumentation
Project-URL: Homepage, https://github.com/impact-ai/opentelemetry-instrumentation-azure-aisearch
Author-email: Impact AI <biz@impact.ai>
License: Apache-2.0
Classifier: Development Status :: 3 - Alpha
Classifier: Intended Audience :: Developers
Classifier: License :: OSI Approved :: Apache Software License
Classifier: Programming Language :: Python :: 3
Classifier: Programming Language :: Python :: 3.8
Classifier: Programming Language :: Python :: 3.9
Classifier: Programming Language :: Python :: 3.10
Classifier: Programming Language :: Python :: 3.11
Classifier: Programming Language :: Python :: 3.12
Requires-Python: >=3.8
Requires-Dist: azure-search-documents>=11.0.0
Requires-Dist: opentelemetry-api~=1.20
Requires-Dist: opentelemetry-instrumentation~=0.45b0
Requires-Dist: opentelemetry-semantic-conventions~=0.45b0
Requires-Dist: wrapt>=1.0.0
